paper_uploads/__init__.py
paper_uploads/apps.py
paper_uploads/conf.py
paper_uploads/exceptions.py
paper_uploads/files.py
paper_uploads/helpers.py
paper_uploads/logging.py
paper_uploads/storage.py
paper_uploads/typing.py
paper_uploads/utils.py
paper_uploads/validators.py
paper_uploads/variations.py
paper_uploads/admin/__init__.py
paper_uploads/admin/base.py
paper_uploads/admin/collection.py
paper_uploads/admin/file.py
paper_uploads/admin/image.py
paper_uploads/admin/svg.py
paper_uploads/forms/__init__.py
paper_uploads/forms/dialogs/__init__.py
paper_uploads/forms/dialogs/base.py
paper_uploads/forms/dialogs/collection.py
paper_uploads/forms/dialogs/file.py
paper_uploads/forms/dialogs/image.py
paper_uploads/forms/dialogs/svg.py
paper_uploads/forms/fields/__init__.py
paper_uploads/forms/fields/base.py
paper_uploads/forms/fields/collection.py
paper_uploads/forms/fields/file.py
paper_uploads/forms/fields/image.py
paper_uploads/forms/widgets/__init__.py
paper_uploads/forms/widgets/base.py
paper_uploads/forms/widgets/collection.py
paper_uploads/forms/widgets/file.py
paper_uploads/forms/widgets/image.py
paper_uploads/forms/widgets/mixins.py
paper_uploads/locale/ru/LC_MESSAGES/django.mo
paper_uploads/locale/ru/LC_MESSAGES/django.po
paper_uploads/locale/ru/LC_MESSAGES/djangojs.mo
paper_uploads/locale/ru/LC_MESSAGES/djangojs.po
paper_uploads/management/__init__.py
paper_uploads/management/conf.py
paper_uploads/management/helpers.py
paper_uploads/management/prompt.py
paper_uploads/management/utils.py
paper_uploads/management/commands/__init__.py
paper_uploads/management/commands/check_uploads.py
paper_uploads/management/commands/clean_uploads.py
paper_uploads/management/commands/create_missing_variations.py
paper_uploads/management/commands/recreate_variations.py
paper_uploads/management/commands/remove_empty_collections.py
paper_uploads/management/commands/remove_variations.py
paper_uploads/migrations/0001_initial.py
paper_uploads-0.18.7.dist-info/LICENSE
paper_uploads-0.18.7.dist-info/METADATA
paper_uploads-0.18.7.dist-info/WHEEL
paper_uploads-0.18.7.dist-info/top_level.txt
paper_uploads-0.18.7.dist-info/RECORD
