Metadata-Version: 2.1
Name: paper-uploads
Version: 0.18.7
Summary: Asynchronous file upload for Django
Home-page: https://github.com/dldevinc/paper-uploads
Author: Mihail Mishakin
Author-email: x896321475@gmail.com
Maintainer: Mihail Mishakin
Maintainer-email: x896321475@gmail.com
License: BSD license
Platform: OS Independent
Classifier: Intended Audience :: Developers
Classifier: Development Status :: 3 - Alpha
Classifier: License :: OSI Approved :: BSD License
Classifier: Operating System :: OS Independent
Classifier: Framework :: Django :: 3.2
Classifier: Framework :: Django :: 4.0
Classifier: Framework :: Django :: 4.1
Classifier: Framework :: Django :: 4.2
Classifier: Framework :: Django :: 5.0
Classifier: Programming Language :: Python
Classifier: Programming Language :: Python :: 3
Classifier: Programming Language :: Python :: 3 :: Only
Classifier: Programming Language :: Python :: 3.9
Classifier: Programming Language :: Python :: 3.10
Classifier: Programming Language :: Python :: 3.11
Classifier: Programming Language :: Python :: 3.12
Classifier: Topic :: Software Development :: Libraries :: Python Modules
Requires-Python: >=3.9
License-File: LICENSE
Requires-Dist: Django >=3.2
Requires-Dist: paper-admin >=7.0
Requires-Dist: variations >=0.3.0
Requires-Dist: Pillow
Requires-Dist: filelock
Requires-Dist: python-magic
Requires-Dist: django-polymorphic
Requires-Dist: anytree
Requires-Dist: inquirer
Provides-Extra: rq
Requires-Dist: django-rq >=2.1 ; extra == 'rq'
